jstemplater/__init__.py
jstemplater/init.py
jstemplater/jstemplater.py
jstemplater-1.0.0.dist-info/licenses/LICENSE
jstemplater-1.0.0.dist-info/METADATA
jstemplater-1.0.0.dist-info/WHEEL
jstemplater-1.0.0.dist-info/top_level.txt
jstemplater-1.0.0.dist-info/RECORD
