Metadata-Version: 2.4
Name: jstemplater
Version: 1.0.0
Summary: Javascript Template Engine for web development
Author: Mark Wayne B. Menorca
License: See LICENSE file
Project-URL: Homepage, https://github.com/yourusername/JS-templater-python
Project-URL: Documentation, https://github.com/yourusername/JS-templater-python#readme
Project-URL: Repository, https://github.com/yourusername/JS-templater-python
Project-URL: Issues, https://github.com/yourusername/JS-templater-python/issues
Keywords: flask,javascript,template,engine,dom,rendering
Classifier: Programming Language :: Python :: 3
Classifier: Operating System :: OS Independent
Classifier: Framework :: Flask
Classifier: Topic :: Internet :: WWW/HTTP :: Dynamic Content
Classifier: Topic :: Software Development :: Libraries :: Python Modules
Requires-Python: >=3.6
License-File: LICENSE
Dynamic: license-file
